amap_mongo/__init__.py
amap_mongo/ali.py
amap_mongo/argument.py
amap_mongo/data.py
amap_mongo/mongo_db.py
amap_mongo/sync.py
amap_mongo/utils.py
async_map_mongo-0.0.5.dist-info/licenses/LICENSE
async_map_mongo-0.0.5.dist-info/METADATA
async_map_mongo-0.0.5.dist-info/WHEEL
async_map_mongo-0.0.5.dist-info/entry_points.txt
async_map_mongo-0.0.5.dist-info/top_level.txt
async_map_mongo-0.0.5.dist-info/RECORD
