Metadata-Version: 2.4
Name: async-map-mongo
Version: 0.0.5
Summary: Asynchronously calls Amap's API to obtain corresponding latitude and longitude coordinates, with API call results stored in a MongoDB database. Provides functionality to query latitude and longitude from MongoDB and export to Excel.
Requires-Python: >=3.12
License-File: LICENSE
Requires-Dist: aiohttp>=3.12.15
Requires-Dist: aiolimiter>=1.2.1
Requires-Dist: openpyxl>=3.1.5
Requires-Dist: pandas>=2.3.1
Requires-Dist: pymongo>=4.14.0
Requires-Dist: python-dotenv>=1.1.1
Requires-Dist: tqdm>=4.67.1
Requires-Dist: transformers>=4.55.0
Dynamic: license-file
